AttentionOdorify/__init__.py
AttentionOdorify/attention_odorify.py
AttentionOdorify-3.0.1.dist-info/METADATA
AttentionOdorify-3.0.1.dist-info/WHEEL
AttentionOdorify-3.0.1.dist-info/top_level.txt
AttentionOdorify-3.0.1.dist-info/RECORD
