Metadata-Version: 2.1
Name: AttentionOdorify
Version: 3.0.1
Summary: Attention based BiLSTM model for Olfactory Analysis
Home-page: UNKNOWN
Author: Harshit Singh Chhabra
Author-email: harshit20009@iiitd.ac.in
License: MIT
Platform: UNKNOWN
Requires-Dist: sklearn
Requires-Dist: torch
Requires-Dist: torchvision
Requires-Dist: numpy
Requires-Dist: pandas
Requires-Dist: matplotlib
Requires-Dist: scikit-plot
Requires-Dist: captum
Requires-Dist: rdkit-pypi
